shortscale/__init__.py
shortscale/shortscale.py
shortscale/tests/bench_shortscale.py
shortscale/tests/test_shortscale.py
shortscale-1.3.2.dist-info/LICENSE
shortscale-1.3.2.dist-info/METADATA
shortscale-1.3.2.dist-info/WHEEL
shortscale-1.3.2.dist-info/entry_points.txt
shortscale-1.3.2.dist-info/top_level.txt
shortscale-1.3.2.dist-info/RECORD
