Metadata-Version: 2.1
Name: shortscale
Version: 1.3.2
Summary: English conversion from number to string
Author-email: Jürgen Leschner <jldec@users.noreply.github.com>
License: (The MIT License)
Project-URL: Home, https://github.com/jldec/shortscale-py
Classifier: License :: OSI Approved :: MIT License
License-File: LICENSE
